flask_regiment/__init__.py
flask_regiment/bulletlog.py
flask_regiment/version.py
flask_regiment-1.1.2.dist-info/LICENSE
flask_regiment-1.1.2.dist-info/WHEEL
flask_regiment-1.1.2.dist-info/METADATA
flask_regiment-1.1.2.dist-info/RECORD
